coopprodsystem/__init__.py
coopprodsystem/storage.py
coopprodsystem/events/__init__.py
coopprodsystem/events/absEventHandler.py
coopprodsystem/events/absProductionEventHandler.py
coopprodsystem/events/eventDefinition.py
coopprodsystem/factory/__init__.py
coopprodsystem/factory/expertiseSchedules.py
coopprodsystem/factory/factory.py
coopprodsystem/factory/productionLine.py
coopprodsystem/factory/station.py
coopprodsystem/factory/stationResourceDefinition.py
coopprodsystem/factory/stationStatus.py
coopprodsystem/factory/stationTransfer.py
coopprodsystem/my_dataclasses/__init__.py
coopprodsystem/my_dataclasses/content.py
coopprodsystem/my_dataclasses/expertiseArgs.py
coopprodsystem/my_dataclasses/locations.py
coopprodsystem/my_dataclasses/resource.py
coopprodsystem/my_dataclasses/resourceUom.py
coopprodsystem/my_dataclasses/unitOfMeasure.py
coopprodsystem/storage/__init__.py
coopprodsystem/storage/exceptions.py
coopprodsystem/storage/storage.py
coopprodsystem/storage/storage_utils.py
coopprodsystem-1.1.dist-info/METADATA
coopprodsystem-1.1.dist-info/WHEEL
coopprodsystem-1.1.dist-info/top_level.txt
coopprodsystem-1.1.dist-info/RECORD
