Metadata-Version: 2.1
Name: coopprodsystem
Version: 1.1
Summary: Package for Modeling production systems
Home-page: https://github.com/tylertjburns/coopprodsystem
Author: tburns
Author-email: tyler.tj.burns@gmail.com
License: MIT
Platform: UNKNOWN
Classifier: Development Status :: 3 - Alpha
Classifier: License :: OSI Approved :: MIT License
Classifier: Programming Language :: Python
Classifier: Programming Language :: Python :: 3.5
Classifier: Programming Language :: Python :: 3.6
Classifier: Topic :: Software Development :: Libraries
Classifier: Topic :: Software Development :: Libraries :: Python Modules
Classifier: Intended Audience :: Developers
Requires-Python: >3.5
Requires-Dist: coopgraph (==1.12)
Requires-Dist: coopstorage (==0.1)
Requires-Dist: cooptools (==1.18)
Requires-Dist: cycler (==0.10.0)
Requires-Dist: frozendict (==2.3.2)
Requires-Dist: kiwisolver (==1.3.2)
Requires-Dist: matplotlib (==3.4.3)
Requires-Dist: numpy (==1.24.2)
Requires-Dist: pandas (==1.5.3)
Requires-Dist: Pillow (==10.0.1)
Requires-Dist: pyparsing (==2.4.7)
Requires-Dist: Pypubsub (==4.0.3)
Requires-Dist: python-dateutil (==2.8.1)
Requires-Dist: pytz (==2021.1)
Requires-Dist: six (==1.16.0)
